nestlog/__init__.py
nestlog-7.dist-info/LICENSE
nestlog-7.dist-info/METADATA
nestlog-7.dist-info/WHEEL
nestlog-7.dist-info/top_level.txt
nestlog-7.dist-info/RECORD
