Metadata-Version: 2.1
Name: nestlog
Version: 7
Summary: Special logger for outputting tree like logs
Home-page: https://gitlab.com/sol-courtney/python-packages/nestlog
Download-URL: https://gitlab.com/sol-courtney/python-packages/nestlog
Author: Sol Courtney
Author-email: sol.courtney@gmail.com
Maintainer: Sol Courtney
Maintainer-email: sol.courtney@gmail.com
License: GNU General Public License v3 (GPLv3)
Project-URL: Documentation, https://nestlog.readthedocs.io
Project-URL: Gitlab Pages, https://sol-courtney.gitlab.io/python-packages/nestlog
Project-URL: Source Code, https://gitlab.com/sol-courtney/python-packages/nestlog
Project-URL: Tracker, https://gitlab.com/sol-courtney/python-packages/nestlog/-/issues
Keywords: Gitlab,Python
Classifier: Development Status :: 4 - Beta
Classifier: Intended Audience :: Developers
Classifier: Intended Audience :: Information Technology
Classifier: License :: OSI Approved :: GNU General Public License v3 (GPLv3)
Classifier: Operating System :: OS Independent
Classifier: Programming Language :: Python
Classifier: Programming Language :: Python :: 3
Classifier: Programming Language :: Python :: 3 :: Only
Classifier: Programming Language :: Python :: 3.10
Classifier: Programming Language :: Python :: 3.11
Classifier: Programming Language :: Python :: 3.9
Classifier: Topic :: Software Development :: Libraries :: Python Modules
Classifier: Topic :: Utilities
Classifier: Typing :: Typed
Requires-Python: >=3.9
License-File: LICENSE
Requires-Dist: click
